README.txt
setup.py
smartopen/__init__.py
smartopen/address.py
smartopen/handlers.py
smartopen/smartopen.py
smartopen/states.py
smartopen.egg-info/PKG-INFO
smartopen.egg-info/SOURCES.txt
smartopen.egg-info/dependency_links.txt
smartopen.egg-info/entry_points.txt
smartopen.egg-info/not-zip-safe
smartopen.egg-info/top_level.txt