Metadata-Version: 1.0
Name: smartopen
Version: 0.1.6
Summary: open text in a browser contextually
Home-page: http://k0s.org/hg/smartopen
Author: Jeff Hammel
Author-email: k0scist@gmail.com
License: GPL
Platform: UNKNOWN
